Metadata-Version: 1.1
Name: assignhooks
Version: 1.0.2
Summary: Instrument code to support obj.__preassign__ / obk.__postassign__ methods. Based on assign package by ryankung
Home-page: https://github.com/patgolez10/assignhooks
Author: patgolez10
Author-email: patgolez10@gmail.com
License: MIT
Platform: any
Classifier: Intended Audience :: Developers
Classifier: Programming Language :: Python
Classifier: Topic :: Software Development :: Libraries :: Python Modules
